[{"name": "benchmarks.TimeSuite.time_additive_multi_model_source", "idx": null, "pretty_name": "benchmarks.TimeSuite.time_additive_multi_model_source", "last_rev": 2324, "last_value": 0.0805394074999981, "last_err": 0.013483483564815636, "prev_value": null, "change_rev": null}, {"name": "benchmarks.TimeSuite.time_apply_passbands", "idx": null, "pretty_name": "benchmarks.TimeSuite.time_apply_passbands", "last_rev": 2324, "last_value": 0.004931941999994175, "last_err": 0.000289929054026706, "prev_value": null, "change_rev": null}, {"name": "benchmarks.TimeSuite.time_apply_white_noise", "idx": null, "pretty_name": "benchmarks.TimeSuite.time_apply_white_noise", "last_rev": 2324, "last_value": 0.019606886499985876, "last_err": 0.0006044063425637545, "prev_value": null, "change_rev": null}, {"name": "benchmarks.TimeSuite.time_approximate_moc_sampler", "idx": null, "pretty_name": "benchmarks.TimeSuite.time_approximate_moc_sampler", "last_rev": 2324, "last_value": 0.023921285499994838, "last_err": 0.00019278041076599046, "prev_value": 0.02509093750001057, "change_rev": [null, 2317]}, {"name": "benchmarks.TimeSuite.time_basic_end_to_end_simulation", "idx": null, "pretty_name": "benchmarks.TimeSuite.time_basic_end_to_end_simulation", "last_rev": 2324, "last_value": 0.7026969094999913, "last_err": 0.04373107279695778, "prev_value": null, "change_rev": null}, {"name": "benchmarks.TimeSuite.time_chained_evaluate_sed", "idx": null, "pretty_name": "benchmarks.TimeSuite.time_chained_evaluate_sed", "last_rev": 2324, "last_value": 0.023533126999979004, "last_err": 0.0007868287837705376, "prev_value": null, "change_rev": null}, {"name": "benchmarks.TimeSuite.time_evaluate_salt3_model", "idx": null, "pretty_name": "benchmarks.TimeSuite.time_evaluate_salt3_model", "last_rev": 2324, "last_value": 0.022009359499946868, "last_err": 0.0009292991107600501, "prev_value": null, "change_rev": null}, {"name": "benchmarks.TimeSuite.time_evaluate_salt3_passbands", "idx": null, "pretty_name": "benchmarks.TimeSuite.time_evaluate_salt3_passbands", "last_rev": 2324, "last_value": 0.005356283750003854, "last_err": 0.00016938982434700606, "prev_value": null, "change_rev": null}, {"name": "benchmarks.TimeSuite.time_evaluate_simple_linear_wavelength_model", "idx": null, "pretty_name": "benchmarks.TimeSuite.time_evaluate_simple_linear_wavelength_model", "last_rev": 2324, "last_value": 0.003630606500010458, "last_err": 0.0002634455378636953, "prev_value": null, "change_rev": null}, {"name": "benchmarks.TimeSuite.time_fnu_to_flam", "idx": null, "pretty_name": "benchmarks.TimeSuite.time_fnu_to_flam", "last_rev": 2324, "last_value": 0.0015756911666547544, "last_err": 0.00017125962969744815, "prev_value": null, "change_rev": null}, {"name": "benchmarks.TimeSuite.time_lightcurve_source", "idx": null, "pretty_name": "benchmarks.TimeSuite.time_lightcurve_source", "last_rev": 2324, "last_value": 0.004357022500007209, "last_err": 0.000838581937528075, "prev_value": null, "change_rev": null}, {"name": "benchmarks.TimeSuite.time_load_ccdvisit_table", "idx": null, "pretty_name": "benchmarks.TimeSuite.time_load_ccdvisit_table", "last_rev": 2324, "last_value": 0.013130486499989047, "last_err": 0.00018802678248969453, "prev_value": 0.01026831575001097, "change_rev": [null, 2265]}, {"name": "benchmarks.TimeSuite.time_load_passbands", "idx": null, "pretty_name": "benchmarks.TimeSuite.time_load_passbands", "last_rev": 2324, "last_value": 0.03230751749998717, "last_err": 0.00097270511653151, "prev_value": null, "change_rev": null}, {"name": "benchmarks.TimeSuite.time_make_and_evaluate_static_sed", "idx": null, "pretty_name": "benchmarks.TimeSuite.time_make_and_evaluate_static_sed", "last_rev": 2324, "last_value": 0.03801482199999384, "last_err": 0.007327570295401332, "prev_value": null, "change_rev": null}, {"name": "benchmarks.TimeSuite.time_make_and_evaluate_step_model", "idx": null, "pretty_name": "benchmarks.TimeSuite.time_make_and_evaluate_step_model", "last_rev": 2324, "last_value": 0.0001686716746032545, "last_err": 1.3039526498752031e-05, "prev_value": null, "change_rev": null}, {"name": "benchmarks.TimeSuite.time_make_evaluate_constant_sed_model", "idx": null, "pretty_name": "benchmarks.TimeSuite.time_make_evaluate_constant_sed_model", "last_rev": 2324, "last_value": 0.03036568049999744, "last_err": 0.0037005752861017037, "prev_value": null, "change_rev": null}, {"name": "benchmarks.TimeSuite.time_make_new_salt3_model", "idx": null, "pretty_name": "benchmarks.TimeSuite.time_make_new_salt3_model", "last_rev": 2324, "last_value": 4.187533399214418e-05, "last_err": 9.574138870723028e-06, "prev_value": null, "change_rev": null}, {"name": "benchmarks.TimeSuite.time_make_simple_linear_wavelength_model", "idx": null, "pretty_name": "benchmarks.TimeSuite.time_make_simple_linear_wavelength_model", "last_rev": 2324, "last_value": 3.030768039776048e-05, "last_err": 4.713411938691489e-06, "prev_value": null, "change_rev": null}, {"name": "benchmarks.TimeSuite.time_make_x1_from_hostmass", "idx": null, "pretty_name": "benchmarks.TimeSuite.time_make_x1_from_hostmass", "last_rev": 2324, "last_value": 1.1248695259999977, "last_err": 0.1989797512479619, "prev_value": null, "change_rev": null}, {"name": "benchmarks.TimeSuite.time_obs_table_get_value_per_row", "idx": null, "pretty_name": "benchmarks.TimeSuite.time_obs_table_get_value_per_row", "last_rev": 2324, "last_value": 0.00010288300934600437, "last_err": 1.743870958777914e-05, "prev_value": null, "change_rev": null}, {"name": "benchmarks.TimeSuite.time_poisson_noise_model", "idx": null, "pretty_name": "benchmarks.TimeSuite.time_poisson_noise_model", "last_rev": 2324, "last_value": 0.000760807400001795, "last_err": 9.121955764512736e-05, "prev_value": null, "change_rev": null}, {"name": "benchmarks.TimeSuite.time_sample_x0_from_distmod", "idx": null, "pretty_name": "benchmarks.TimeSuite.time_sample_x0_from_distmod", "last_rev": 2324, "last_value": 9.244241393457555e-05, "last_err": 2.309143153957663e-05, "prev_value": null, "change_rev": null}, {"name": "benchmarks.TimeSuite.time_sample_x1_from_hostmass", "idx": null, "pretty_name": "benchmarks.TimeSuite.time_sample_x1_from_hostmass", "last_rev": 2324, "last_value": 1.2462657572376796e-05, "last_err": 1.910502352634865e-06, "prev_value": null, "change_rev": null}]