[{"name": "benchmarks.TimeSuite.time_additive_multi_model_source", "idx": null, "pretty_name": "benchmarks.TimeSuite.time_additive_multi_model_source", "last_rev": 2370, "last_value": 0.07875647249998963, "last_err": 0.014793365759973568, "prev_value": null, "change_rev": null}, {"name": "benchmarks.TimeSuite.time_apply_passbands", "idx": null, "pretty_name": "benchmarks.TimeSuite.time_apply_passbands", "last_rev": 2370, "last_value": 0.0019940902500010793, "last_err": 0.000399463985288847, "prev_value": 0.004995789166666024, "change_rev": [null, 2360]}, {"name": "benchmarks.TimeSuite.time_apply_white_noise", "idx": null, "pretty_name": "benchmarks.TimeSuite.time_apply_white_noise", "last_rev": 2370, "last_value": 0.019606616500027485, "last_err": 0.0006980741103219846, "prev_value": null, "change_rev": null}, {"name": "benchmarks.TimeSuite.time_approximate_moc_sampler", "idx": null, "pretty_name": "benchmarks.TimeSuite.time_approximate_moc_sampler", "last_rev": 2370, "last_value": 0.02468777649997378, "last_err": 0.0010697377481930443, "prev_value": 0.05808919150000236, "change_rev": [null, 2263]}, {"name": "benchmarks.TimeSuite.time_basic_end_to_end_simulation", "idx": null, "pretty_name": "benchmarks.TimeSuite.time_basic_end_to_end_simulation", "last_rev": 2370, "last_value": 0.6962044350000127, "last_err": 0.055356730494404545, "prev_value": null, "change_rev": null}, {"name": "benchmarks.TimeSuite.time_chained_evaluate_sed", "idx": null, "pretty_name": "benchmarks.TimeSuite.time_chained_evaluate_sed", "last_rev": 2370, "last_value": 0.023533126999979004, "last_err": 0.0015279705463239418, "prev_value": null, "change_rev": null}, {"name": "benchmarks.TimeSuite.time_evaluate_salt3_model", "idx": null, "pretty_name": "benchmarks.TimeSuite.time_evaluate_salt3_model", "last_rev": 2370, "last_value": 0.021786517499990055, "last_err": 0.0011860577209780701, "prev_value": null, "change_rev": null}, {"name": "benchmarks.TimeSuite.time_evaluate_salt3_passbands", "idx": null, "pretty_name": "benchmarks.TimeSuite.time_evaluate_salt3_passbands", "last_rev": 2370, "last_value": 0.0053501655000189885, "last_err": 0.0002455601679224521, "prev_value": null, "change_rev": null}, {"name": "benchmarks.TimeSuite.time_evaluate_simple_linear_wavelength_model", "idx": null, "pretty_name": "benchmarks.TimeSuite.time_evaluate_simple_linear_wavelength_model", "last_rev": 2370, "last_value": 0.0002847891025648772, "last_err": 0.0003193530737805917, "prev_value": 0.0002352637500002214, "change_rev": [2361, 2363]}, {"name": "benchmarks.TimeSuite.time_fnu_to_flam", "idx": null, "pretty_name": "benchmarks.TimeSuite.time_fnu_to_flam", "last_rev": 2370, "last_value": 0.0015756911666547544, "last_err": 0.00022842560499238319, "prev_value": null, "change_rev": null}, {"name": "benchmarks.TimeSuite.time_lightcurve_source", "idx": null, "pretty_name": "benchmarks.TimeSuite.time_lightcurve_source", "last_rev": 2370, "last_value": 0.004409352833334879, "last_err": 0.0008498792604823256, "prev_value": null, "change_rev": null}, {"name": "benchmarks.TimeSuite.time_load_ccdvisit_table", "idx": null, "pretty_name": "benchmarks.TimeSuite.time_load_ccdvisit_table", "last_rev": 2370, "last_value": 0.01314414200001579, "last_err": 0.00040053239207078604, "prev_value": 0.01026831575001097, "change_rev": [null, 2265]}, {"name": "benchmarks.TimeSuite.time_load_passbands", "idx": null, "pretty_name": "benchmarks.TimeSuite.time_load_passbands", "last_rev": 2370, "last_value": 0.03217436450000832, "last_err": 0.0013347695675501386, "prev_value": null, "change_rev": null}, {"name": "benchmarks.TimeSuite.time_make_and_evaluate_static_sed", "idx": null, "pretty_name": "benchmarks.TimeSuite.time_make_and_evaluate_static_sed", "last_rev": 2370, "last_value": 0.038253505499994844, "last_err": 0.0072644296566448975, "prev_value": null, "change_rev": null}, {"name": "benchmarks.TimeSuite.time_make_and_evaluate_step_model", "idx": null, "pretty_name": "benchmarks.TimeSuite.time_make_and_evaluate_step_model", "last_rev": 2370, "last_value": 0.00016635939855083723, "last_err": 2.492720223483496e-05, "prev_value": null, "change_rev": null}, {"name": "benchmarks.TimeSuite.time_make_evaluate_constant_sed_model", "idx": null, "pretty_name": "benchmarks.TimeSuite.time_make_evaluate_constant_sed_model", "last_rev": 2370, "last_value": 0.03014230850001809, "last_err": 0.004476675182396469, "prev_value": null, "change_rev": null}, {"name": "benchmarks.TimeSuite.time_make_new_salt3_model", "idx": null, "pretty_name": "benchmarks.TimeSuite.time_make_new_salt3_model", "last_rev": 2370, "last_value": 4.18088303570739e-05, "last_err": 1.2359431209347978e-05, "prev_value": null, "change_rev": null}, {"name": "benchmarks.TimeSuite.time_make_simple_linear_wavelength_model", "idx": null, "pretty_name": "benchmarks.TimeSuite.time_make_simple_linear_wavelength_model", "last_rev": 2370, "last_value": 3.027520565551681e-05, "last_err": 6.2309719301754415e-06, "prev_value": null, "change_rev": null}, {"name": "benchmarks.TimeSuite.time_make_x1_from_hostmass", "idx": null, "pretty_name": "benchmarks.TimeSuite.time_make_x1_from_hostmass", "last_rev": 2370, "last_value": 0.9236172224999706, "last_err": 0.23935860582672036, "prev_value": null, "change_rev": null}, {"name": "benchmarks.TimeSuite.time_obs_table_get_value_per_row", "idx": null, "pretty_name": "benchmarks.TimeSuite.time_obs_table_get_value_per_row", "last_rev": 2370, "last_value": 0.00010298691428585828, "last_err": 1.6240128869534578e-05, "prev_value": null, "change_rev": null}, {"name": "benchmarks.TimeSuite.time_poisson_noise_model", "idx": null, "pretty_name": "benchmarks.TimeSuite.time_poisson_noise_model", "last_rev": 2370, "last_value": 0.0007482619333283461, "last_err": 9.437579740820045e-05, "prev_value": null, "change_rev": null}, {"name": "benchmarks.TimeSuite.time_sample_x0_from_distmod", "idx": null, "pretty_name": "benchmarks.TimeSuite.time_sample_x0_from_distmod", "last_rev": 2370, "last_value": 0.00011230088144368884, "last_err": 2.4733464359055804e-05, "prev_value": null, "change_rev": null}, {"name": "benchmarks.TimeSuite.time_sample_x1_from_hostmass", "idx": null, "pretty_name": "benchmarks.TimeSuite.time_sample_x1_from_hostmass", "last_rev": 2370, "last_value": 1.247130672749374e-05, "last_err": 2.334740469253583e-06, "prev_value": null, "change_rev": null}]